{
  "objectInfo" : {
    "id" : "7H8IBLJtkNgcRliBNTeXa7",
    "name" : "Dictionary2_Project_Versioning_2",
    "type" : "DICTIONARY",
    "metadata" : {
      "modelVersion" : {
        "major" : 1,
        "minor" : 0
      },
      "repoInfo" : {
        "repoHandle" : "7H8IBLJtkNgcRliBNTeXa7"
      },
      "contextAttributes" : [ ],
      "additionalInfo" : {
        "description" : "example&&&!!!!",
        "contentType" : "Binary",
        "documentState" : "VALID"
      }
    }
  },
  "dataFileExtension" : "json",
  "objectRefs" : [ ]
}