{
  "objectInfo" : {
    "id" : "aQV2Qu0w7XmiqSP83TFgEZ",
    "name" : "labeler",
    "type" : "LABELER",
    "metadata" : {
      "modelVersion" : {
        "major" : 1,
        "minor" : 0
      },
      "repoInfo" : {
        "repoHandle" : "aQV2Qu0w7XmiqSP83TFgEZ"
      },
      "contextAttributes" : [ ],
      "additionalInfo" : {
        "description" : null,
        "contentType" : "Binary",
        "documentState" : "INVALID"
      }
    }
  },
  "dataFileExtension" : "json",
  "objectRefs" : [ ]
}