{
  "objectInfo" : {
    "id" : "6AqU6u6PIKkgPMF7ACEqWm",
    "name" : "Cleanse_Versioning_Remove_Spaces",
    "type" : "CLEANSE",
    "metadata" : {
      "modelVersion" : {
        "major" : 1,
        "minor" : 0
      },
      "repoInfo" : {
        "repoHandle" : "6AqU6u6PIKkgPMF7ACEqWm"
      },
      "contextAttributes" : [ ],
      "additionalInfo" : {
        "description" : "Remove Spaces",
        "contentType" : "Binary",
        "documentState" : "VALID"
      }
    }
  },
  "dataFileExtension" : "json",
  "objectRefs" : [ ]
}