{
  "objectInfo" : {
    "id" : "cxGpuK5lHsdfikz4SkuvCi",
    "name" : "Mapping1",
    "type" : "DTEMPLATE",
    "metadata" : {
      "modelVersion" : {
        "major" : 0,
        "minor" : 0
      },
      "repoInfo" : {
        "repoHandle" : "010ARW17000000000047"
      },
      "contextAttributes" : [ {
        "name" : "id",
        "value" : "@1"
      } ],
      "additionalInfo" : {
        "description" : "",
        "contentType" : "JSON",
        "documentState" : "INVALID"
      }
    }
  },
  "dataFileExtension" : "zip",
  "objectRefs" : [ {
    "id" : "8oLHWZXWwDteBDqTq7rR6p",
    "name" : "cleanse_target_connection",
    "type" : "Connection",
    "metadata" : {
      "modelVersion" : {
        "major" : 0,
        "minor" : 0
      },
      "repoInfo" : {
        "repoHandle" : "010ARW0B000000000005"
      },
      "contextAttributes" : null,
      "additionalInfo" : {
        "description" : "Target Flat File Connection.",
        "contentType" : "JSON",
        "documentState" : "COMPLETE"
      }
    },
    "path" : "/SYS"
  }, {
    "id" : "2TTOVzCFAqtg4XHR6SasGt",
    "name" : "Cleanse",
    "type" : "CLEANSE",
    "metadata" : {
      "modelVersion" : {
        "major" : 1,
        "minor" : 0
      },
      "repoInfo" : {
        "repoHandle" : "2TTOVzCFAqtg4XHR6SasGt"
      },
      "contextAttributes" : null,
      "additionalInfo" : {
        "description" : null,
        "contentType" : "Binary",
        "documentState" : "VALID"
      }
    },
    "path" : "/Explore/Default"
  }, {
    "id" : "9cSK2TIyxQuf3y2p25ENa1",
    "name" : "cleanse_source_connection",
    "type" : "Connection",
    "metadata" : {
      "modelVersion" : {
        "major" : 0,
        "minor" : 0
      },
      "repoInfo" : {
        "repoHandle" : "010ARW0B000000000004"
      },
      "contextAttributes" : null,
      "additionalInfo" : {
        "description" : "Source Flat File Connection.",
        "contentType" : "JSON",
        "documentState" : "COMPLETE"
      }
    },
    "path" : "/SYS"
  } ]
}