{"id":"ee5c7c6f-734e-4571-b0a9-17e0b3f57d17","profileKey":708,"version":0,"name":"p_user1","orgId":"d9q1IR1On2LhOkfT19PTcT","description":null,"frsId":"1eccmmcAoZtldCLZLgxWUw","frsProjectId":"7X7gwPLOPOUiJLPBjdsI0t","connectionId":"8DEAgb9bKWZlqt0nmlCEGy","createdBy":"avKMuZ7GqCkhRuC4EA9kw2","createdByName":"slaroia","createTime":1655893137304,"updatedBy":"avKMuZ7GqCkhRuC4EA9kw2","updatedByName":"slaroia","updateTime":1655893137318,"isFilterEnabled":false,"runtimeOptions":{"id":"1fcd7574-7ed1-4813-8c84-fbb47a6acb69","scheduleId":null,"runtimeEnvironmentId":null,"defaultEmailNotification":true,"profileAdvProps":{"maxTopN":null,"maxPatterns":null,"maxPatternThresholdPercent":null,"maxRanks":null,"inferDateTime":true,"detectOutliers":true,"enableClaireAnomalyDetection":null,"maxColumnsPerMapping":null,"minNoOfRowsForSplitMapping":null,"maxMemory":null,"maxPercentMemory":null,"defaultBufferBlockSize":null,"dtmBufferSize":null,"lineSequentialBufferLength":null,"stopOnErrors":null}},"source":{"id":"b7b3953f-3ad7-45e7-b7ba-bdc41feb0d7e","name":"cities_100","fields":[{"id":"41415ec9-a4ef-450a-9a7f-8f8931be7db9","name":"State","dataType":"nstring","precision":255,"scale":0,"pcType":"UNISTRING","order":1,"isDeleted":false,"isMetadataUpdated":false},{"id":"51d2a101-d5d3-41e7-946d-0c9f963df8c7","name":"City","dataType":"nstring","precision":255,"scale":0,"pcType":"UNISTRING","order":0,"isDeleted":false,"isMetadataUpdated":false}],"dataSourceType":"DELIMITED","properties":{"dataSourceType":"DELIMITED","delimiter":",","textQualifier":"\"","escapeCharacter":"","sourceFileName":"cities_100","firstDataRow":2,"headerLineNo":1},"sourceType":"DATASOURCE"},"profileableFields":[{"id":"bc7e15fa-8546-4f1e-9e23-d156a526c114","isDeleted":false,"appliedBy":"USER","columnKey":10001,"sourceName":"cities_100","fieldName":"State","fieldType":"DATASOURCEFIELD"},{"id":"5aaebf28-422e-47e8-a008-47314bb72777","isDeleted":true,"appliedBy":"USER","columnKey":10002,"sourceName":"cities_100","fieldName":"City","fieldType":"DATASOURCEFIELD"}],"samplingOptions":{"id":null,"rows":-1,"samplingType":"ALL_ROWS"},"drillDownType":"ON"}