{
  "objectInfo" : {
    "id" : "5OwrhUNqH5Xf9HXMCFRSmM",
    "name" : "Versioning_PreBuiltParse_2",
    "type" : "PARSE",
    "metadata" : {
      "modelVersion" : {
        "major" : 1,
        "minor" : 0
      },
      "repoInfo" : {
        "repoHandle" : "5OwrhUNqH5Xf9HXMCFRSmM"
      },
      "contextAttributes" : [ ],
      "additionalInfo" : {
        "description" : "Versioning_PreBuiltParse_2",
        "contentType" : "Binary",
        "documentState" : "VALID"
      }
    }
  },
  "dataFileExtension" : "json",
  "objectRefs" : [ ]
}