{
  "objectInfo" : {
    "id" : "0SEL3HiN2G5faOVm7hk1cx",
    "name" : "Parse_Versioning_Dict",
    "type" : "PARSE",
    "metadata" : {
      "modelVersion" : {
        "major" : 1,
        "minor" : 0
      },
      "repoInfo" : {
        "repoHandle" : "0SEL3HiN2G5faOVm7hk1cx"
      },
      "contextAttributes" : [ ],
      "additionalInfo" : {
        "description" : null,
        "contentType" : "Binary",
        "documentState" : "VALID"
      }
    }
  },
  "dataFileExtension" : "json",
  "objectRefs" : [ {
    "id" : "2vQRSqpAQapiEhJsuJSzQu",
    "name" : "Dictionary2_Project_Versioning",
    "type" : "DICTIONARY",
    "metadata" : {
      "modelVersion" : {
        "major" : 1,
        "minor" : 0
      },
      "repoInfo" : {
        "repoHandle" : "2vQRSqpAQapiEhJsuJSzQu"
      },
      "contextAttributes" : [ ],
      "additionalInfo" : {
        "description" : null,
        "contentType" : "Binary",
        "documentState" : "VALID"
      }
    },
    "path" : "/Explore/Auto_Project_Git_Version"
  } ]
}