{
  "objectInfo" : {
    "id" : "dQ3MaCyurqTgyLe0lsrxWL",
    "name" : "Parse_Versioning_Dict",
    "type" : "PARSE",
    "metadata" : {
      "modelVersion" : {
        "major" : 1,
        "minor" : 0
      },
      "repoInfo" : {
        "repoHandle" : "dQ3MaCyurqTgyLe0lsrxWL"
      },
      "contextAttributes" : [ ],
      "additionalInfo" : {
        "description" : null,
        "contentType" : "Binary",
        "documentState" : "VALID"
      }
    }
  },
  "dataFileExtension" : "json",
  "objectRefs" : [ {
    "id" : "6A7RjSfhw5HkIKY24NVZ8s",
    "name" : "Dictionary2_Project_Versioning",
    "type" : "DICTIONARY",
    "metadata" : {
      "modelVersion" : {
        "major" : 1,
        "minor" : 0
      },
      "repoInfo" : {
        "repoHandle" : "6A7RjSfhw5HkIKY24NVZ8s"
      },
      "contextAttributes" : [ ],
      "additionalInfo" : {
        "description" : null,
        "contentType" : "Binary",
        "documentState" : "VALID"
      }
    },
    "path" : "/Explore/Auto_Project_Git_Version"
  } ]
}